{
  "accession_number": "90.1",
  "artist": "Mississippian artist",
  "classification": "Ceramics",
  "continent": "Americas",
  "country": "United States",
  "creditline": "The Ethel Morrison Van Derlip Fund",
  "culture": "Mississippian",
  "curator_approved": 0,
  "dated": "1250–1499",
  "department": "Arts of the Americas",
  "description": "",
  "dimension": "2 5/16 x 7 1/16 in. (5.87 x 17.94 cm)",
  "id": 3906,
  "image": "invalid",
  "image_copyright": null,
  "image_height": 2424,
  "image_width": 3885,
  "inscription": null,
  "life_date": "North America",
  "markings": null,
  "medium": "Ceramic",
  "object_name": "Bowl, Vessel (Hodges Style)",
  "portfolio": null,
  "provenance": null,
  "restricted": 0,
  "rights_type": "Public Domain",
  "room": "Not on View",
  "signed": null,
  "style": null,
  "text": null,
  "title": "Bowl"
}
