{
  "accession_number": "2019.117.3",
  "artist": "Fred Hagstrom",
  "classification": "Prints",
  "continent": "\"Americas\"",
  "country": "\"United States\"",
  "creditline": "Gift of Fred Hagstrom and Sandra Spadaccini",
  "culture": null,
  "curator_approved": 0,
  "dated": "1988",
  "department": "Global Contemporary Art",
  "description": "",
  "dimension": "63 1/4 × 41 1/2 in. (160.66 × 105.41 cm) (sheet)",
  "id": 135783,
  "image": "invalid",
  "image_copyright": "© Fred Hagstrom",
  "image_height": null,
  "image_width": null,
  "inscription": null,
  "life_date": "Fred Hagstrom, American, born 1954",
  "markings": null,
  "medium": "Color woodcut, collagraph, and monotype",
  "object_name": "Print",
  "portfolio": null,
  "provenance": "Fred Hagstrom, St. Paul; given to MIA, 2019.",
  "restricted": 0,
  "rights_type": "In Copyright",
  "room": "Not on View",
  "signed": "LRC in white pencil: Hagstrom / Dream & Lie",
  "style": null,
  "text": null,
  "title": "The Dream and Lie"
}
