{
  "accession_number": "2018.131.2",
  "artist": "Hugo Gellert, International Workers Order, New York",
  "classification": "Prints",
  "continent": "\"Americas\"",
  "country": "\"United States\"",
  "creditline": "Gift of Mary Ryan and Bruce Lebowitz",
  "culture": null,
  "curator_approved": 1,
  "dated": "1943",
  "department": "Arts of the Americas",
  "description": "",
  "dimension": "15 1/8 × 13 1/16 in. (38.42 × 33.18 cm) (image)\r\n20 × 15 15/16 in. (50.8 × 40.48 cm) (sheet)",
  "id": 131230,
  "image": "valid",
  "image_copyright": "© Estate of Hugo Gellert",
  "image_height": 6664,
  "image_width": 5431,
  "inscription": "on inner left side of folded sheet; in LLC, in pencil: HG-66 (16)",
  "life_date": "1892–1985",
  "markings": null,
  "medium": "Color screenprint and lithograph, letterpress",
  "object_name": "Print with text",
  "portfolio": "\"Century of the Common Man: Two Speeches by Henry A. Wallace\" portfolio",
  "provenance": "Mary Ryan and Bruce Lebowitz, New York; given to MIA, 2018.",
  "restricted": 0,
  "rights_type": "In Copyright",
  "room": "Not on View",
  "signed": "LRC in margin, in black ink: HUGO GELLERT",
  "style": null,
  "text": "An outline drawing of a handshake floats like a giant banner above a view of audience members at a political meeting. In the foreground are three men: one white, one black, and one Asian. They face the same direction and have serious expressions on their faces.",
  "title": "Century of the Common Man: Learning to Think and Work Together"
}
