{
  "accession_number": "2019.91.33",
  "artist": "Ryūkyū",
  "classification": "Textiles",
  "continent": "Asia",
  "country": "Japan",
  "creditline": "Gift of Thomas Murray",
  "culture": "Ryukyu",
  "curator_approved": 0,
  "dated": "19th century",
  "department": "Asian Art",
  "description": "",
  "dimension": "8 7/8 × 6 1/4 in. (22.54 × 15.88 cm)",
  "id": 131580,
  "image": "valid",
  "image_copyright": null,
  "image_height": 3000,
  "image_width": 2400,
  "inscription": null,
  "life_date": null,
  "markings": "LLC, verso: Murray Collection label: OKI 6179",
  "medium": "Cloth: cotton, bingata (stencil resist with applied pigments)",
  "object_name": "Fragment",
  "portfolio": null,
  "provenance": null,
  "restricted": 0,
  "rights_type": "Public Domain",
  "room": "Not on View",
  "signed": null,
  "style": null,
  "text": null,
  "title": "Fragment decorated with pine, plum, and chrysanthemum over stylized pine bark"
}
