{
  "accession_number": "2019.91.30.5.2",
  "artist": "Unknown",
  "classification": "Musical Instruments",
  "continent": "Asia",
  "country": "Russia",
  "creditline": "Gift of Thomas Murray in memory of Joseph G. Gerena",
  "culture": null,
  "curator_approved": 0,
  "dated": "late 19th–early 20th century",
  "department": "Asian Art",
  "description": "",
  "dimension": "10 × 1 1/2 × 7/8 in. (25.4 × 3.81 × 2.22 cm)",
  "id": 131577,
  "image": "valid",
  "image_copyright": null,
  "image_height": 890,
  "image_width": 721,
  "inscription": null,
  "life_date": null,
  "markings": null,
  "medium": "Wood",
  "object_name": "Drum beater",
  "portfolio": null,
  "provenance": null,
  "restricted": 0,
  "rights_type": "No Known Copyright",
  "room": "Not on View",
  "signed": null,
  "style": null,
  "text": null,
  "title": "Drum beater [from a shaman costume set]"
}
