{
  "accession_number": "2007.35.51",
  "artist": "Photographer: Harry Callahan",
  "classification": "Photographs",
  "continent": "Americas",
  "country": "United States",
  "creditline": "Gift of Frederick B. Scheel",
  "culture": null,
  "curator_approved": 0,
  "dated": "1950",
  "department": "Arts of the Americas",
  "description": "",
  "dimension": "7 5/8 x 9 5/8 in. (19.37 x 24.45 cm) (image)\r\n7 15/16 x 10 in. (20.16 x 25.4 cm) (sheet)",
  "id": 99690,
  "image": "valid",
  "image_copyright": "© Estate Harry Callahan / PaceWildensteinMacGill, New York",
  "image_height": 2815,
  "image_width": 3560,
  "inscription": "Signature",
  "life_date": "Harry Callahan, Photographer, American, 1912–1999",
  "markings": null,
  "medium": "Gelatin silver print",
  "object_name": null,
  "portfolio": null,
  "provenance": null,
  "restricted": 0,
  "rights_type": "In Copyright",
  "room": "Not on View",
  "signed": "LRC below image, in pencil: [Harry Callahan]",
  "style": null,
  "text": null,
  "title": "Chicago"
}
