{
  "accession_number": "2002.29.19",
  "artist": "Pierre Daura",
  "classification": "Drawings",
  "continent": "Americas",
  "country": "United States",
  "creditline": "Gift of Martha R. Daura",
  "culture": null,
  "curator_approved": 0,
  "dated": "c. 1930–39",
  "department": "Arts of the Americas",
  "description": "",
  "dimension": "19 3/16 x 24 11/16 in. (48.74 x 62.71 cm)",
  "id": 61190,
  "image": "valid",
  "image_copyright": "© Martha Daura / Estate of Pierre Daura. Some rights reserved.",
  "image_height": 5071,
  "image_width": 6512,
  "inscription": null,
  "life_date": "American (born Spain), 1896–1976",
  "markings": "<CANSON & MONTGOLFIER FRANCE>",
  "medium": "Charcoal on paper",
  "nationality": "American",
  "object_name": null,
  "portfolio": null,
  "provenance": null,
  "restricted": 1,
  "rights_type": "In Copyright–Non-Commercial Use",
  "room": "Not on View",
  "signed": null,
  "style": null,
  "text": null,
  "title": "Church at St. Cirq-Lapopie, France"
}
