{
  "accession_number": "99.157.5",
  "artist": "India (Rajasthan)",
  "classification": "Textiles",
  "continent": "Asia",
  "country": "India",
  "creditline": "Gift of Nobuko Kajitani",
  "culture": null,
  "curator_approved": 0,
  "dated": "18th century",
  "department": "Asian Art",
  "description": "",
  "dimension": "38 x 1 7/16 in. (96.52 x 3.66 cm)",
  "id": 11993,
  "image": "valid",
  "image_copyright": null,
  "image_height": 1661,
  "image_width": 4311,
  "inscription": "Inscription",
  "life_date": null,
  "markings": "[150], in blue ink, on one end",
  "medium": "Cotton, silk, embroidered",
  "nationality": "Indian",
  "object_name": "Border",
  "portfolio": null,
  "provenance": null,
  "restricted": 0,
  "rights_type": "Public Domain",
  "room": "Not on View",
  "signed": null,
  "style": null,
  "text": null,
  "title": "Border"
}
