{
  "accession_number": "98.149.32.4",
  "artist": "Manufacturer: JB Martin",
  "classification": "Textiles",
  "continent": "Americas",
  "country": "United States",
  "creditline": "Gift of The Fashion Institute of Technology",
  "culture": null,
  "curator_approved": 0,
  "dated": "1970–75",
  "department": "Arts of the Americas",
  "description": "",
  "dimension": "30 1/2 x 35 3/8 in. (77.47 x 89.85 cm)",
  "id": 10383,
  "image": "valid",
  "image_copyright": "© J.B. Martin Company, Inc.",
  "image_height": 3429,
  "image_width": 3855,
  "inscription": "Label",
  "life_date": "America",
  "markings": "'20.2', adhesive label, on reverse",
  "medium": "Velvet, printed",
  "object_name": "Velvet panel",
  "portfolio": null,
  "provenance": null,
  "restricted": 0,
  "rights_type": "In Copyright–Educational Use",
  "room": "Not on View",
  "signed": null,
  "style": null,
  "text": null,
  "title": "Velvet panel"
}
