{
  "accession_number": "2021.101.262",
  "artist": "Walter Gramatté",
  "classification": "Drawings",
  "continent": null,
  "country": null,
  "creditline": "Gift of The Eckhardt-Gramatté Foundation",
  "culture": null,
  "curator_approved": 1,
  "dated": "1923 (?)",
  "department": "European Art",
  "description": "",
  "dimension": "12 5/8 × 10 5/8 in. (32.1 × 27 cm) (sheet)",
  "id": 142111,
  "image": "invalid",
  "image_copyright": null,
  "image_height": 4646,
  "image_width": 3915,
  "inscription": "LLC of sheet in red pencil, on verso: 170",
  "life_date": "German, 1897–1929",
  "markings": null,
  "medium": "Graphite on paper",
  "object_name": "Drawing",
  "portfolio": null,
  "provenance": null,
  "restricted": 0,
  "rights_type": "Public Domain",
  "room": "Not on View",
  "signed": null,
  "style": null,
  "text": null,
  "title": "Self-Portrait I"
}
