{
  "exhibition_id": 2447,
  "exhibition_department": "Prints and Drawings",
  "exhibition_title": "Félix Bracquemond: Etcher of Birds",
  "exhibition_description": null,
  "begin": 2016,
  "end": 2017,
  "display_date": "Friday, November 25, 2016 - Sunday, May 07, 2017",
  "objects": [
    284,
    8274,
    50575,
    50581,
    50583,
    54143,
    54149,
    54151,
    54156,
    54158,
    54172,
    54175,
    54180,
    54183,
    55987,
    55993,
    63128,
    65421,
    125491,
    125494,
    125496,
    125497,
    125500,
    125516,
    125517,
    126038,
    126039
  ],
  "venues": [
    {
      "venue": "Minneapolis Institute of Art",
      "begin": 2016,
      "end": 2017,
      "display_date": "Friday, November 25, 2016 - Sunday, May 7, 2017"
    }
  ]
}
