{
  "accession_number": "P.118",
  "artist": "Georg Pencz",
  "classification": "Prints",
  "continent": "\"Europe\"",
  "country": "\"Germany\"",
  "creditline": "The William M. Ladd Collection\r\nGift of Herschel V. Jones, 1916",
  "culture": null,
  "curator_approved": 0,
  "dated": "16th century",
  "department": "European Art",
  "description": "",
  "dimension": "5 5/16 x 7 5/16 in. (13.49 x 18.57 cm) (image)",
  "id": 7248,
  "image": "invalid",
  "image_copyright": null,
  "image_height": null,
  "image_width": null,
  "inscription": null,
  "life_date": "Georg Pencz, German, active c. 1500–1550",
  "markings": null,
  "medium": "Engraving",
  "object_name": null,
  "portfolio": null,
  "provenance": null,
  "restricted": 0,
  "rights_type": "Public Domain",
  "room": "Not on View",
  "signed": null,
  "style": null,
  "text": null,
  "title": "Thetis and  Chiron"
}
