{
  "accession_number": "P.4,957",
  "artist": "Mary Cassatt",
  "classification": "Prints",
  "continent": "\"Americas\"",
  "country": "\"United States\"",
  "creditline": "The William M. Ladd Collection\r\nGift of Herschel V. Jones, 1916",
  "culture": null,
  "curator_approved": 0,
  "dated": "c. 1896–1897",
  "department": "Arts of the Americas",
  "description": "",
  "dimension": "9 1/2 x 12 7/16 in. (24.13 x 31.59 cm) (plate)\r\n12 3/4 x 16 13/16 in. (32.39 x 42.7 cm) (sheet)",
  "id": 7410,
  "image": "valid",
  "image_copyright": null,
  "image_height": 4106,
  "image_width": 5411,
  "inscription": "Inscr. in pencil at bottom: \"First state Les marionettes Etat 36",
  "life_date": "1844–1926",
  "markings": "Watermark: Crowned shield with the letter B",
  "medium": "Drypoint and aquatint, printed in color from two plates",
  "object_name": "Print",
  "portfolio": null,
  "provenance": "(Frederick Keppel, New York). William M. Ladd, Portland, Ore., sold to Jones, 1916: Herschel V. Jones, Minneapolis; given to MIA, 1916.",
  "restricted": 0,
  "rights_type": "No Copyright–United States",
  "room": "G353",
  "signed": "Signed in pencil LR margin: Mary Cassatt",
  "style": null,
  "text": null,
  "title": "The Barefooted Child"
}
