{
  "accession_number": "87.17.1",
  "artist": "Photographer: H. Arthur Taussig",
  "classification": "Photographs",
  "continent": "\"Americas\"",
  "country": "\"United States\"",
  "creditline": "The Ethel Morrison Van Derlip Fund",
  "culture": null,
  "curator_approved": 0,
  "dated": "1981",
  "department": "Global Contemporary Art",
  "description": "",
  "dimension": "15 1/16 x 19 in. (38.26 x 48.26 cm) (image)\r\n15 15/16 x 19 15/16 in. (40.48 x 50.64 cm) (sheet)",
  "id": 25232,
  "image": "valid",
  "image_copyright": "© H. Arthur Taussig",
  "image_height": 3433,
  "image_width": 4354,
  "inscription": null,
  "life_date": "H. Arthur Taussig, Photographer, American, born 1941",
  "markings": null,
  "medium": "Dye bleach color print",
  "object_name": null,
  "portfolio": null,
  "provenance": null,
  "restricted": 1,
  "rights_type": "In Copyright–Educational Use",
  "room": "Not on View",
  "signed": null,
  "style": null,
  "text": null,
  "title": "Optical Collage: Alfred Stieglitz"
}
