{
  "accession_number": "88.38",
  "artist": "Jan Buckman",
  "classification": "Basketry",
  "continent": "\"Americas\"",
  "country": "\"United States\"",
  "creditline": "Gift of the Textile Council",
  "culture": null,
  "curator_approved": 0,
  "dated": "1988",
  "department": "Global Contemporary Art",
  "description": "",
  "dimension": "4 15/16 x 4 in. (12.54 x 10.16 cm)",
  "id": 25544,
  "image": "valid",
  "image_copyright": "© Jan Buckman",
  "image_height": 5376,
  "image_width": 3617,
  "inscription": null,
  "life_date": "Jan Buckman, American, born 1949",
  "markings": null,
  "medium": "Linen",
  "object_name": "Basket",
  "portfolio": null,
  "provenance": null,
  "restricted": 0,
  "rights_type": "In Copyright",
  "room": "Not on View",
  "signed": null,
  "style": null,
  "text": null,
  "title": "Basket"
}
