{
  "accession_number": "2020.80.136",
  "artist": "Theodore Roszak",
  "classification": "Drawings",
  "continent": "Americas",
  "country": "United States",
  "creditline": "Gift of the estate of Theodore Roszak",
  "culture": null,
  "curator_approved": 0,
  "dated": "1952",
  "department": "Arts of the Americas",
  "description": "",
  "dimension": "26 x 40 in.",
  "id": 138337,
  "image": "valid",
  "image_copyright": null,
  "image_height": 7182,
  "image_width": 4850,
  "inscription": null,
  "life_date": "American (born Prussia, now Poland), 1907–1981",
  "markings": null,
  "medium": "Pen and ink on paper",
  "nationality": "American (born Prussia, now Poland)",
  "object_name": "Drawing",
  "portfolio": null,
  "provenance": null,
  "restricted": 0,
  "rights_type": "In Copyright",
  "room": "Not on View",
  "signed": null,
  "style": null,
  "text": null,
  "title": "The Furies"
}
