{
  "accession_number": "2005.148.1",
  "artist": "China",
  "classification": "Ceramics",
  "continent": "Asia",
  "country": "China",
  "creditline": "Gift of Noah and Susan Eisenberg",
  "culture": null,
  "curator_approved": 0,
  "dated": "2nd century BCE",
  "department": "Asian Art",
  "description": "",
  "dimension": "21 x 3 9/16 x 3 1/2 in. (53.34 x 9.05 x 8.89 cm)",
  "id": 98753,
  "image": "valid",
  "image_copyright": null,
  "image_height": 3000,
  "image_width": 937,
  "inscription": null,
  "life_date": null,
  "markings": null,
  "medium": "Ceramic, pigment",
  "nationality": "Chinese",
  "object_name": "Female figure",
  "portfolio": null,
  "provenance": null,
  "restricted": 0,
  "rights_type": "Public Domain",
  "room": "Not on View",
  "signed": null,
  "style": null,
  "text": null,
  "title": "Female figure"
}
