{
  "accession_number": "P.13, 443",
  "artist": "Josef Albers; Printer: Printed at Yale University by Josef Albers",
  "classification": "Prints",
  "continent": "Americas",
  "country": "United States",
  "creditline": "The Ethel Morrison Van Derlip Fund, 1965",
  "culture": null,
  "curator_approved": 1,
  "dated": "1958 (printed 1959)",
  "department": "Arts of the Americas",
  "description": "",
  "dimension": "5 1/16 x 13 9/16 in. (12.86 x 34.45 cm) (image)\r\n15 x 22 1/4 in. (38.1 x 56.52 cm) (sheet)",
  "id": 66514,
  "image": "invalid",
  "image_copyright": "© The Josef and Anni Albers Foundation / Artists Rights Society (ARS), New York",
  "image_height": null,
  "image_width": null,
  "inscription": "Titled in pencil, LL: Duo F",
  "life_date": "American (born Germany), 1888–1976",
  "markings": "Numbered in pencil, LL: 12/20",
  "medium": "Inkless intaglio embossed from a brass plate",
  "nationality": "American (born Germany)",
  "object_name": "Print",
  "portfolio": "Intaglio Duo suite",
  "provenance": "Collectors Club of Minnesota; sold to MIA, 1965.",
  "restricted": 1,
  "rights_type": "In Copyright",
  "room": "Not on View",
  "signed": "Signed, dated in pencil, LR: Albers '59",
  "style": null,
  "text": null,
  "title": "Intaglio Duo F"
}
