{
  "accession_number": "P.17, 423",
  "artist": "Thomas Rowlandson; Etcher: Thomas Rowlandson; Publisher: Rudolph Ackermann",
  "classification": "Prints",
  "continent": "Europe",
  "country": "England",
  "creditline": "The Minnich Collection\r\nThe Ethel Morrison Van Derlip Fund, 1966",
  "culture": null,
  "curator_approved": 0,
  "dated": "September 1, 1822",
  "department": "European Art",
  "description": "",
  "dimension": "5 x 7 3/4 in. (12.7 x 19.69 cm) (sheet)",
  "id": 77412,
  "image": "valid",
  "image_copyright": null,
  "image_height": 3061,
  "image_width": 4906,
  "inscription": null,
  "life_date": "British, 1756–1827",
  "markings": null,
  "medium": "Hand-colored etching, aquatint",
  "nationality": "British",
  "object_name": null,
  "portfolio": "From The History of Johnny Quae Genus, The Little Foundling of the Late Doctor Syntax",
  "provenance": null,
  "restricted": 0,
  "rights_type": "Public Domain",
  "room": "Not on View",
  "signed": null,
  "style": null,
  "text": null,
  "title": "Quae Genus With A Portrait Painter"
}
