{
  "accession_number": "2002.201.2",
  "artist": "Lakȟóta artist",
  "classification": "Leatherwork",
  "continent": "Americas",
  "country": "United States",
  "creditline": "Gift of Don Piccard and Brennan Piccard Greene, Collection of Jean F. Piccard, c. 1916",
  "culture": "probably Lakȟóta",
  "curator_approved": 0,
  "dated": null,
  "department": "Arts of the Americas",
  "description": "",
  "dimension": "76-11/16 x 1-1/4 in. (194.8 x 3.2 cm)",
  "id": 49716,
  "image": "invalid",
  "image_copyright": null,
  "image_height": null,
  "image_width": null,
  "inscription": null,
  "life_date": "North America, Great Plains region",
  "markings": null,
  "medium": "Animal hide, beads, metal studs",
  "object_name": "Belt",
  "portfolio": null,
  "provenance": null,
  "restricted": 0,
  "rights_type": "Public Domain",
  "room": "Not on View",
  "signed": null,
  "style": null,
  "text": null,
  "title": "Belt"
}
