{
  "accession_number": "2013.29.1198",
  "artist": "Kishino Kan",
  "classification": "Ceramics",
  "continent": "Asia",
  "country": "Japan",
  "creditline": "Gift of the Clark Center for Japanese Art & Culture",
  "culture": null,
  "curator_approved": 0,
  "dated": "2010",
  "department": "Asian Art",
  "description": "",
  "dimension": "22 1/2 × 20 × 20 in. (57.15 × 50.8 × 50.8 cm)",
  "id": 116970,
  "image": "valid",
  "image_copyright": null,
  "image_height": 5616,
  "image_width": 3744,
  "inscription": null,
  "life_date": "Kishino Kan, Japanese, born 1975",
  "markings": null,
  "medium": "Stoneware",
  "object_name": "Large pot (ōgame)",
  "portfolio": null,
  "provenance": null,
  "restricted": 0,
  "rights_type": "No Known Copyright",
  "room": "Not on View",
  "signed": null,
  "style": null,
  "text": null,
  "title": "Large pot"
}
