{
  "accession_number": "2003.236.1101",
  "artist": "Unknown",
  "classification": "Dolls, Toys and Games",
  "continent": null,
  "country": null,
  "creditline": "Gift of Katherine Kierland Herberger",
  "culture": null,
  "curator_approved": 0,
  "dated": "20th century",
  "department": "Arts of the Americas",
  "description": "",
  "dimension": "5 1/2 x 2 9/16 x 2 1/2 in. (13.97 x 6.51 x 6.35 cm)",
  "id": 90573,
  "image": "valid",
  "image_copyright": null,
  "image_height": 2574,
  "image_width": 1676,
  "inscription": "Inscriptions\r\n\r\non back, in raised letters: [2/PAT. PEND.]\r\non bottom, in ink: [K/2]",
  "life_date": null,
  "markings": null,
  "medium": "Iron, pigment, paper",
  "nationality": null,
  "object_name": "U.S. Mailbox still bank",
  "portfolio": null,
  "provenance": null,
  "restricted": 0,
  "rights_type": "Public Domain",
  "room": "Not on View",
  "signed": null,
  "style": null,
  "text": null,
  "title": "U.S. Mailbox still bank"
}
