{
  "accession_number": "23.39",
  "artist": "England",
  "classification": "Ceramics",
  "continent": "Europe",
  "country": "England",
  "creditline": null,
  "culture": null,
  "curator_approved": 0,
  "dated": "18th century",
  "department": "European Art",
  "description": "",
  "dimension": "10-1/8 x 7 x 5",
  "id": 14015,
  "image": "invalid",
  "image_copyright": null,
  "image_height": null,
  "image_width": null,
  "inscription": null,
  "life_date": null,
  "markings": null,
  "medium": "Ceramic, metal",
  "nationality": "English",
  "object_name": "Jug",
  "portfolio": null,
  "provenance": null,
  "restricted": 0,
  "rights_type": "Public Domain",
  "room": "Not on View",
  "signed": null,
  "style": null,
  "text": null,
  "title": "Jug"
}
