{
  "accession_number": "2023.80.25",
  "artist": "United States",
  "classification": "Photographs",
  "continent": "Americas",
  "country": "United States",
  "creditline": "Gift of Peter J. Cohen",
  "culture": null,
  "curator_approved": 0,
  "dated": null,
  "department": "Global Contemporary Art",
  "description": "",
  "dimension": "5 3/8 x 3 1/4 in. (13.6 x 8.2 cm)",
  "id": 145262,
  "image": "invalid",
  "image_copyright": null,
  "image_height": null,
  "image_width": null,
  "inscription": null,
  "life_date": null,
  "markings": null,
  "medium": "Gelatin silver print",
  "nationality": null,
  "object_name": "Photograph",
  "portfolio": null,
  "provenance": null,
  "restricted": 0,
  "rights_type": "No Known Copyright",
  "room": "Not on View",
  "signed": null,
  "style": null,
  "text": null,
  "title": "Untitled [portrait of a seated woman]"
}
