{
  "accession_number": "93.94",
  "artist": "O. Kruschki",
  "classification": "Drawings",
  "continent": "Europe",
  "country": "Germany",
  "creditline": "Gift of Mary and Katharine Harlow",
  "culture": null,
  "curator_approved": 0,
  "dated": "1879",
  "department": "European Art",
  "description": "",
  "dimension": "13 1/4 x 19 3/8 in. (33.66 x 49.21 cm) (sheet)",
  "id": 28300,
  "image": "invalid",
  "image_copyright": null,
  "image_height": null,
  "image_width": null,
  "inscription": "Signature, Date, Mark",
  "life_date": null,
  "markings": "Watermark laid down",
  "medium": "Watercolor on white wove paper",
  "nationality": null,
  "object_name": "Watercolor",
  "portfolio": null,
  "provenance": null,
  "restricted": 0,
  "rights_type": "Public Domain",
  "room": "Not on View",
  "signed": "[O Kruschki 79] lower left",
  "style": null,
  "text": null,
  "title": "Mountain Chalet"
}
