{
  "accession_number": "93.70.5",
  "artist": "Photographer: Thomas F. Arndt",
  "classification": "Photographs",
  "continent": "\"Americas\"",
  "country": "\"United States\"",
  "creditline": "Gift of Lora and Martin G. Weinstein",
  "culture": null,
  "curator_approved": 0,
  "dated": "20th century",
  "department": "Arts of the Americas",
  "description": "",
  "dimension": "12 x 18 1/8 in. (30.48 x 46.04 cm) (image)\r\n16 x 19 15/16 in. (40.64 x 50.64 cm) (sheet)",
  "id": 4618,
  "image": "valid",
  "image_copyright": "© Tom Arndt",
  "image_height": 2412,
  "image_width": 3647,
  "inscription": null,
  "life_date": "Thomas F. Arndt, Photographer, American, born 1944",
  "markings": null,
  "medium": "Gelatin silver print",
  "object_name": null,
  "portfolio": null,
  "provenance": null,
  "restricted": 1,
  "rights_type": "In Copyright–Educational Use",
  "room": "Not on View",
  "signed": null,
  "style": null,
  "text": null,
  "title": "Eau Claire, Wisconsin, No. 1"
}
