{
  "accession_number": "P.76.28.47",
  "artist": "William Weege",
  "classification": "Prints",
  "continent": "Americas",
  "country": "United States",
  "creditline": "Gift of Dr. and Mrs. Frederick P. Nause",
  "culture": null,
  "curator_approved": 0,
  "dated": "1976",
  "department": "Global Contemporary Art",
  "description": "",
  "dimension": "22 x 18 13/16 in. (55.88 x 47.78 cm) (image, flush)\r\n22 x 30 in. (55.88 x 76.2 cm) (sheet)",
  "id": 54387,
  "image": "invalid",
  "image_copyright": "© William Weege",
  "image_height": null,
  "image_width": null,
  "inscription": "Titled LC, in pencil: 'YES! VIRGINIA THERE REALLY WAS A TURKEY'",
  "life_date": "American, 1935–2020",
  "markings": "Numbered LC, in pencil: XIX\r\nPublisher's (?) blindstamp, LRC\r\nWatermark:: Arches France",
  "medium": "Color screenprint with flocking",
  "nationality": "American",
  "object_name": "Print",
  "portfolio": null,
  "provenance": "Dr. and Mrs. Frederick P. Nause; given to MIA, 1976.",
  "restricted": 0,
  "rights_type": "In Copyright",
  "room": "Not on View",
  "signed": "Signed and dated LR, in pencil: Weege 76",
  "style": null,
  "text": null,
  "title": "Yes! Virginia, There Really Was a Turkey"
}
