{
  "accession_number": "31.84.5a,b",
  "artist": "China",
  "classification": "Ceramics",
  "continent": "\"Asia\"",
  "country": "\"China\"",
  "creditline": "Gift of Mrs. Eugene J. Carpenter and Olivia Carpenter Coan in memory of Eugene J. Carpenter",
  "culture": null,
  "curator_approved": 0,
  "dated": null,
  "department": "Asian Art",
  "description": "",
  "dimension": "9 1/4in. (23.5cm)",
  "id": 15594,
  "image": "invalid",
  "image_copyright": null,
  "image_height": null,
  "image_width": null,
  "inscription": null,
  "life_date": "China",
  "markings": null,
  "medium": "Porcelain",
  "object_name": "Vase",
  "portfolio": null,
  "provenance": null,
  "restricted": 0,
  "rights_type": "Public Domain",
  "room": "G327",
  "signed": null,
  "style": null,
  "text": null,
  "title": "Vase"
}
