{
  "exhibition_id": 665,
  "exhibition_department": "Historic: Prints and Drawings",
  "exhibition_title": "Félix Buhot: Master Etcher of the 19th Century",
  "exhibition_description": null,
  "begin": 2004,
  "end": 2004,
  "display_date": "Saturday, April 10, 2004 - Sunday, October 10, 2004",
  "public_info": 0,
  "objects": [
    9249,
    9256,
    9798,
    50595,
    50598,
    50611,
    50659,
    50660,
    50699,
    50703,
    50706,
    50754,
    50756,
    50760,
    54187,
    54190,
    54191,
    54199,
    54310,
    54330,
    54338,
    54341,
    54355,
    54357,
    54359,
    54368,
    56002,
    56005,
    65620
  ],
  "venues": [
    {
      "venue": "Minneapolis Institute of Art",
      "begin": 2004,
      "end": 2004,
      "display_date": "Saturday, April 10, 2004 - Sunday, October 10, 2004"
    }
  ]
}
