{
  "accession_number": "2011.70.6",
  "artist": "Southern Bullom (Sherbro) artist",
  "classification": "Accessories, Woodwork",
  "continent": "Africa",
  "country": "Sierra Leone",
  "creditline": "Gift of William Siegmann",
  "culture": "Southern Bullom (Sherbro)",
  "curator_approved": 0,
  "dated": null,
  "department": "Arts of Global Africa",
  "description": "",
  "dimension": "15 x 10 3/8 x 10 1/2 in. (38.1 x 26.35 x 26.67 cm) (approx.)",
  "id": 113478,
  "image": "valid",
  "image_copyright": null,
  "image_height": 7216,
  "image_width": 5412,
  "inscription": "Inscription\r\n\r\nat interior edge, in black on white: [86-67-1]",
  "life_date": "Sierra Leone",
  "markings": null,
  "medium": "Wood",
  "nationality": "Sierra Leonean",
  "object_name": "Mask",
  "portfolio": null,
  "provenance": null,
  "restricted": 0,
  "rights_type": "Public Domain",
  "room": "Not on View",
  "signed": null,
  "style": null,
  "text": null,
  "title": "Humoy helmet mask"
}
