{
  "accession_number": "2002.279.7",
  "artist": "Adolf Dehn",
  "classification": "Prints",
  "continent": "Americas",
  "country": "United States",
  "creditline": "Gift of Mrs. Adolf Dehn",
  "culture": null,
  "curator_approved": 0,
  "dated": "1928",
  "department": "Arts of the Americas",
  "description": "",
  "dimension": null,
  "id": 38035,
  "image": "valid",
  "image_copyright": "© Estate of Adolf Arthur Dehn",
  "image_height": 4280,
  "image_width": 6235,
  "inscription": "Signature; Inscription",
  "life_date": "American, 1895–1968",
  "markings": "'Adolf Dehn 1928', LR; '24/30', LL; '320', verso, UL; '81', UR",
  "medium": "Lithograph on chiné applique",
  "nationality": "American",
  "object_name": null,
  "portfolio": null,
  "provenance": null,
  "restricted": 0,
  "rights_type": "In Copyright",
  "room": "Not on View",
  "signed": null,
  "style": null,
  "text": null,
  "title": "Lohengrin"
}
