{
  "accession_number": "2008.41.149",
  "artist": "Tai Pam",
  "classification": "Textiles",
  "continent": "Asia",
  "country": "Vietnam",
  "creditline": "Gift of Richard L. Simmons",
  "culture": "Tai Pam",
  "curator_approved": 0,
  "dated": "20th century",
  "department": "Asian Art",
  "description": "",
  "dimension": "32 7/8 x 23 3/4 in. (83.5 x 60.33 cm)",
  "id": 106094,
  "image": "valid",
  "image_copyright": null,
  "image_height": 3574,
  "image_width": 2775,
  "inscription": null,
  "life_date": null,
  "markings": null,
  "medium": "Cotton, wool",
  "nationality": null,
  "object_name": "Skirt",
  "portfolio": null,
  "provenance": null,
  "restricted": 0,
  "rights_type": "Public Domain",
  "room": "Not on View",
  "signed": null,
  "style": null,
  "text": null,
  "title": "Skirt"
}
