{
  "accession_number": "2008.50.6",
  "artist": "Photographer: Edward S. Curtis",
  "classification": "Photographs",
  "continent": "Americas",
  "country": "United States",
  "creditline": "Gift of Beverly and John Rollwagen",
  "culture": null,
  "curator_approved": 0,
  "dated": "1921",
  "department": "Arts of the Americas",
  "description": "",
  "dimension": "15 3/8 x 11 1/2 in. (39.05 x 29.21 cm) (image)\r\n16 7/16 x 12 1/8 in. (41.75 x 30.8 cm) (sight)\r\n21 3/4 x 16 3/4 in. (55.25 x 42.55 cm) (mount)\r\n22 5/16 x 18 in. (56.67 x 45.72 cm) (mat)",
  "id": 106207,
  "image": "invalid",
  "image_copyright": "This work is in the public domain in the United States. The copyright has expired because its first publication occurred prior to January 1, 1923.",
  "image_height": null,
  "image_width": null,
  "inscription": "Title, Date and Inscription\r\n\r\nULC, printed in brown: [Plate 414]",
  "life_date": "Edward S. Curtis, Photographer, American, 1868–1952",
  "markings": null,
  "medium": "Photogravure on tissue",
  "object_name": null,
  "portfolio": "The North American Indian",
  "provenance": null,
  "restricted": 0,
  "rights_type": "No Copyright–United States",
  "room": "Not on View",
  "signed": "in lower margin, printed in brown: [CHAíWA - TEWA  From Copyright Photograph 1905 by E.S. Curtis  Photogravure Suffolk Eng. Co. Boston]",
  "style": null,
  "text": null,
  "title": "Chaíwa--Tewa"
}
