{
  "accession_number": "2008.45.15",
  "artist": "Miao artist",
  "classification": "Clothing",
  "continent": "Asia",
  "country": "China",
  "creditline": "The Helen Jones Fund for Asian Art",
  "culture": "Miao",
  "curator_approved": 0,
  "dated": "c. 2007",
  "department": "Asian Art",
  "description": "",
  "dimension": "28 1/16 x 47 3/16 in. (71.28 x 119.86 cm) (at waistband)",
  "id": 106408,
  "image": "valid",
  "image_copyright": null,
  "image_height": 3718,
  "image_width": 4478,
  "inscription": null,
  "life_date": "Miao artist, China",
  "markings": null,
  "medium": "Cotton, silk, hemp",
  "object_name": "Skirt",
  "portfolio": null,
  "provenance": null,
  "restricted": 0,
  "rights_type": "Public Domain",
  "room": "Not on View",
  "signed": null,
  "style": null,
  "text": null,
  "title": "Skirt"
}
