{
  "accession_number": "98.68.29",
  "artist": "China",
  "classification": "Ceramics",
  "continent": "Asia",
  "country": "China",
  "creditline": "Gift of fu\r\nnds from Ruth and Bruce Dayton",
  "culture": null,
  "curator_approved": 0,
  "dated": "15th-16th century",
  "department": "Asian Art",
  "description": "",
  "dimension": "7 7/8 x 2 11/16 x 2in. (20 x 6.8 x 5.1cm)",
  "id": 31011,
  "image": "invalid",
  "image_copyright": null,
  "image_height": null,
  "image_width": null,
  "inscription": null,
  "life_date": null,
  "markings": null,
  "medium": "Glazed ceramic",
  "nationality": "Chinese",
  "object_name": "Musician",
  "portfolio": "From a large tileworks retinue",
  "provenance": null,
  "restricted": 0,
  "rights_type": "Public Domain",
  "room": "G215",
  "signed": null,
  "style": null,
  "text": null,
  "title": "Musician"
}
