{
  "accession_number": "98.68.46",
  "artist": "China",
  "classification": "Ceramics",
  "continent": "Asia",
  "country": "China",
  "creditline": "Gift of Ruth and Bruce Dayton",
  "culture": null,
  "curator_approved": 0,
  "dated": "15th-16th century",
  "department": "Asian Art",
  "description": "",
  "dimension": "7 15/16 x 3 x 2 3/16in. (20.2 x 7.6 x 5.6cm)",
  "id": 31030,
  "image": "valid",
  "image_copyright": null,
  "image_height": 3454,
  "image_width": 2802,
  "inscription": null,
  "life_date": null,
  "markings": null,
  "medium": "Glazed ceramic",
  "nationality": "Chinese",
  "object_name": "Attendant",
  "portfolio": "From a large tileworks retinue",
  "provenance": null,
  "restricted": 0,
  "rights_type": "Public Domain",
  "room": "G215",
  "signed": null,
  "style": null,
  "text": null,
  "title": "Attendant"
}
