{
  "accession_number": "2004.261.20",
  "artist": "China for export",
  "classification": "Ceramics",
  "continent": "Asia",
  "country": "China",
  "creditline": "Gift of Leo and Doris Hodroff",
  "culture": null,
  "curator_approved": 0,
  "dated": "c. 1745",
  "department": "European Art",
  "description": "",
  "dimension": "7/8 x 8 7/8 x 8 7/8 in. (2.22 x 22.48 x 22.48 cm)",
  "id": 96802,
  "image": "invalid",
  "image_copyright": null,
  "image_height": null,
  "image_width": null,
  "inscription": "Stickers",
  "life_date": null,
  "markings": "on bottom: two collector's stickers",
  "medium": "Glazed ceramic",
  "nationality": "Chinese",
  "object_name": "Plate with Holy Family in grissaille",
  "portfolio": null,
  "provenance": null,
  "restricted": 0,
  "rights_type": "Public Domain",
  "room": "G209",
  "signed": null,
  "style": "Chinese export",
  "text": null,
  "title": "Plate with Holy Family in grissaille"
}
