{
  "accession_number": "41.61.1",
  "artist": "Emerson T. Quannie",
  "classification": "Drawings",
  "continent": "Americas",
  "country": "United States",
  "creditline": "Gift of Mrs. C. C. Bovey",
  "culture": null,
  "curator_approved": 0,
  "dated": "1930s",
  "department": "Arts of the Americas",
  "description": "",
  "dimension": "13 x 16 1/2in. (33 x 41.9cm)",
  "id": 16523,
  "image": "valid",
  "image_copyright": "Copyright of the artist, artist's estate, or assignees",
  "image_height": 3928,
  "image_width": 4757,
  "inscription": null,
  "life_date": "American, Hopituh Shi-nu-mu (Hopi), 1916–1948",
  "markings": null,
  "medium": "Watercolor",
  "object_name": "Watercolor",
  "portfolio": null,
  "provenance": null,
  "restricted": 1,
  "rights_type": "In Copyright–Rights-holder(s) Unlocatable",
  "room": "Not on View",
  "signed": "LR, ink: [E.T. Quannie]",
  "style": null,
  "text": null,
  "title": "Indian Dancers"
}
