{
  "accession_number": "2016.136.8",
  "artist": "Mark Tobey",
  "classification": "Prints, Works on Paper",
  "continent": "Americas",
  "country": "United States",
  "creditline": "Gift of Raymond A. and Ruth A. Reister",
  "culture": null,
  "curator_approved": 0,
  "dated": "1961",
  "department": "Arts of the Americas",
  "description": "",
  "dimension": "9 1/8 × 6 5/16 in. (23.18 × 16.03 cm) (sight, recto)\r\n9 1/8 × 6 1/4 in. (23.18 × 15.88 cm) (sight, verso)\r\n17 1/16 × 14 × 1 in. (43.34 × 35.56 × 2.54 cm) (outer frame)",
  "id": 125081,
  "image": "valid",
  "image_copyright": "© 2016 Estate of Mark Tobey / Artists Rights Society (ARS), New York",
  "image_height": 3852,
  "image_width": 2729,
  "inscription": null,
  "life_date": "American, 1890–1976",
  "markings": null,
  "medium": "Color monotype in tempera",
  "object_name": "Monotype",
  "portfolio": null,
  "provenance": "Ruth A. Reister, Minneapolis; Estate of Ruth A. Reister; bequethed to MIA, 2016",
  "restricted": 0,
  "rights_type": "In Copyright",
  "room": "Not on View",
  "signed": "LRC, in blue crayon: Tobey 61",
  "style": null,
  "text": null,
  "title": "Portrait Head (recto and verso)"
}
