{
  "accession_number": "P.78.55.2",
  "artist": "Wanda Gág; Publisher: The Spiral Press, New York",
  "classification": "Prints",
  "continent": "Americas",
  "country": "United States",
  "creditline": "Gift of Dr. John E. Larkin, Jr.",
  "culture": null,
  "curator_approved": 0,
  "dated": "1929",
  "department": "Arts of the Americas",
  "description": "",
  "dimension": "5 1/2 x 3 in. (13.97 x 7.62 cm) (image)\r\n5 7/8 x 3 1/4 in. (14.92 x 8.26 cm) (sheet)",
  "id": 57270,
  "image": "valid",
  "image_copyright": null,
  "image_height": 5520,
  "image_width": 2860,
  "inscription": null,
  "life_date": "American, 1893–1946",
  "markings": null,
  "medium": "Linoleum cut",
  "nationality": "American",
  "object_name": null,
  "portfolio": null,
  "provenance": null,
  "restricted": 1,
  "rights_type": "No Known Copyright",
  "room": "Not on View",
  "signed": null,
  "style": null,
  "text": null,
  "title": "Paper Cutter"
}
