{
  "accession_number": "P.11, 704",
  "artist": "Donald Shaw MacLaughlan",
  "classification": "Prints",
  "continent": "Americas",
  "country": "United States",
  "creditline": null,
  "culture": null,
  "curator_approved": 0,
  "dated": "1920",
  "department": "Arts of the Americas",
  "description": "",
  "dimension": "9 5/16 x 6 1/2 in. (23.65 x 16.51 cm) (plate)",
  "id": 57392,
  "image": "invalid",
  "image_copyright": null,
  "image_height": null,
  "image_width": null,
  "inscription": "Signature",
  "life_date": "American (born Canada), 1876–1938",
  "markings": null,
  "medium": "Etching",
  "nationality": "American (born Canada)",
  "object_name": null,
  "portfolio": null,
  "provenance": null,
  "restricted": 0,
  "rights_type": "No Copyright–United States",
  "room": "Not on View",
  "signed": "In lower right margin",
  "style": null,
  "text": null,
  "title": "Trees and Fields"
}
