{
  "accession_number": "P.82.40.114",
  "artist": "Winslow Homer",
  "classification": "Prints",
  "continent": "Americas",
  "country": "United States",
  "creditline": "Gift of Dr. and Mrs. Robert D. Semsch",
  "culture": null,
  "curator_approved": 0,
  "dated": "1858",
  "department": "Arts of the Americas",
  "description": "",
  "dimension": "5 7/8 x 9 1/4 in. (14.9 x 23.5 cm)",
  "id": 57959,
  "image": "valid",
  "image_copyright": null,
  "image_height": 8076,
  "image_width": 5555,
  "inscription": null,
  "life_date": "American, 1836–1910",
  "markings": null,
  "medium": "Wood engraving",
  "nationality": "American",
  "object_name": null,
  "portfolio": "From Harper's Weekly, New York, November 13, 1858, p. 729;",
  "provenance": null,
  "restricted": 0,
  "rights_type": "Public Domain",
  "room": "Not on View",
  "signed": "In plate",
  "style": null,
  "text": null,
  "title": "Driving Home the Corn"
}
